kitehistory/__init__.py
kitehistory/config.py
kitehistory/kitehistory.py
kitehistory/scaffold.py
kitehistory-1.4.dist-info/DESCRIPTION.rst
kitehistory-1.4.dist-info/METADATA
kitehistory-1.4.dist-info/RECORD
kitehistory-1.4.dist-info/WHEEL
kitehistory-1.4.dist-info/entry_points.txt
kitehistory-1.4.dist-info/metadata.json
kitehistory-1.4.dist-info/top_level.txt
