Metadata-Version: 2.0
Name: kitehistory
Version: 1.4
Summary: Kite History API wrapper
Home-page: https://github.com/mr-karan/kiteHistory/
Author: Karan Sharma
Author-email: karansharma1295@gmail.com
License: MIT
Platform: UNKNOWN
Classifier: Development Status :: 5 - Production/Stable
Classifier: License :: OSI Approved :: MIT License
Classifier: Operating System :: POSIX
Classifier: Intended Audience :: Developers
Classifier: Intended Audience :: End Users/Desktop
Classifier: Natural Language :: English
Classifier: Operating System :: OS Independent
Classifier: Programming Language :: Python :: 3 :: Only
Classifier: Programming Language :: Python :: 3.3
Classifier: Programming Language :: Python :: 3.4
Classifier: Programming Language :: Python :: 3.5
Classifier: Topic :: Software Development :: Libraries
Classifier: Topic :: Software Development :: Libraries :: Python Modules
Requires-Dist: Jinja2 (==2.9.6)
Requires-Dist: MarkupSafe (==1.0)
Requires-Dist: PyYAML (==3.12)
Requires-Dist: appdirs (==1.4.3)
Requires-Dist: astroid (==1.5.3)
Requires-Dist: autopep8 (==1.3.2)
Requires-Dist: bokeh (==0.12.5)
Requires-Dist: certifi (==2017.4.17)
Requires-Dist: chardet (==3.0.4)
Requires-Dist: idna (==2.5)
Requires-Dist: isort (==4.2.13)
Requires-Dist: kiteconnect (==3.4.1)
Requires-Dist: lazy-object-proxy (==1.3.1)
Requires-Dist: mccabe (==0.6.1)
Requires-Dist: numpy (==1.12.1)
Requires-Dist: packaging (==16.8)
Requires-Dist: pandas (==0.20.1)
Requires-Dist: pkginfo (==1.4.1)
Requires-Dist: pycodestyle (==2.3.1)
Requires-Dist: pylint (==1.7.1)
Requires-Dist: pyparsing (==2.2.0)
Requires-Dist: python-dateutil (==2.6.0)
Requires-Dist: pytz (==2017.2)
Requires-Dist: requests (==2.17.3)
Requires-Dist: requests-toolbelt (==0.8.0)
Requires-Dist: six (==1.10.0)
Requires-Dist: tornado (==4.5.1)
Requires-Dist: tqdm (==4.14.0)
Requires-Dist: twine (==1.9.1)
Requires-Dist: urllib3 (==1.21.1)
Requires-Dist: websocket-client (==0.40.0)
Requires-Dist: wrapt (==1.10.10)
